<?xml version="1.0" encoding="UTF-8"?>
<METADATA>
  <LAYER alias="Reversiones">
    <TABLENAME>exp_reversion</TABLENAME>
    <PRIMARYKEY>
    	<PKELEMENT>id_reversion</PKELEMENT>
    </PRIMARYKEY>
    <RECORDSET>
      <FIELD>
        <FIELDNAME>tramo</FIELDNAME>
        <DOMAINREADER>
            <DRTYPE>db</DRTYPE>
            <DRDBSCHEMA>audasa_expropiaciones</DRDBSCHEMA>
        	<DRDBTABLE>tramos</DRDBTABLE>
        	<DRDBCOLUMNVALUE>id_tramo</DRDBCOLUMNVALUE>
        	<DRDBCOLUMNALIAS>nombre_tramo</DRDBCOLUMNALIAS>
        </DOMAINREADER>
      </FIELD>
      <FIELD>
        <FIELDNAME>numero_reversion</FIELDNAME>
		<VALIDATIONRULE>INTEGER_POSITIVE</VALIDATIONRULE>
		<VALIDATIONRULE>MANDATORY</VALIDATIONRULE>
      </FIELD>
  </RECORDSET>
  </LAYER>
  <LAYER alias="Fincas">
    <TABLENAME>exp_finca</TABLENAME>
    <PRIMARYKEY>
        <PKELEMENT>id_finca</PKELEMENT>
    </PRIMARYKEY>
    <RECORDSET>
      <FIELD>
        <FIELDNAME>tramo</FIELDNAME>
        <DOMAINREADER>
            <DRTYPE>db</DRTYPE>
        	<DRDBTABLE>tramos</DRDBTABLE>
        	<DRDBCOLUMNVALUE>id_tramo</DRDBCOLUMNVALUE>
        	<DRDBCOLUMNALIAS>nombre_tramo</DRDBCOLUMNALIAS>
        </DOMAINREADER>
      </FIELD>
      <FIELD>
        <FIELDNAME>unidad_constructiva</FIELDNAME>
        <DOMAINREADER>
            <DRTYPE>db</DRTYPE>
        	<DRDBTABLE>uc</DRDBTABLE>
        	<DRDBCOLUMNVALUE>id_uc</DRDBCOLUMNVALUE>
        	<DRDBCOLUMNALIAS>nombre_uc</DRDBCOLUMNALIAS>
        	<DRDBFOREIGNKEY>id_tramo</DRDBFOREIGNKEY>
		</DOMAINREADER>
      </FIELD>
      <FIELD>
        <FIELDNAME>ayuntamiento</FIELDNAME>
		<DOMAINREADER>
		    <DRTYPE>db</DRTYPE>
        	<DRDBTABLE>ayuntamientos</DRDBTABLE>
        	<DRDBCOLUMNVALUE>id_ayuntamiento</DRDBCOLUMNVALUE>
        	<DRDBCOLUMNALIAS>nombre_ayuntamiento</DRDBCOLUMNALIAS>
        	<DRDBFOREIGNKEY>id_uc</DRDBFOREIGNKEY>
       </DOMAINREADER>
      </FIELD>
      <FIELD>
        <FIELDNAME>parroquia_subtramo</FIELDNAME>
        <DOMAINREADER>
            <DRTYPE>db</DRTYPE>
        	<DRDBTABLE>parroquias_subtramos</DRDBTABLE>
        	<DRDBCOLUMNVALUE>id_parroquia</DRDBCOLUMNVALUE>
        	<DRDBCOLUMNALIAS>nombre_parroquia</DRDBCOLUMNALIAS>
        	<DRDBFOREIGNKEY>id_uc</DRDBFOREIGNKEY>
        	<DRDBFOREIGNKEY>id_ayuntamiento</DRDBFOREIGNKEY>
        </DOMAINREADER>
      </FIELD>
      <FIELD>
        <FIELDNAME>numero_finca</FIELDNAME>
		<VALIDATIONRULE>INTEGER_POSITIVE</VALIDATIONRULE>
		<DOMAINREADER>
			<DRTYPE>db</DRTYPE>
			<DRDBTABLE>exp_finca</DRDBTABLE>
			<DRDBCOLUMNVALUE>numero_finca</DRDBCOLUMNVALUE>
			<DRDBCOLUMNALIAS>numero_finca</DRDBCOLUMNALIAS>
			<DRDBFOREIGNKEY>tramo</DRDBFOREIGNKEY>
			<DRDBFOREIGNKEY>unidad_constructiva</DRDBFOREIGNKEY>
			<DRDBFOREIGNKEY>ayuntamiento</DRDBFOREIGNKEY>
			<DRDBFOREIGNKEY>parroquia_subtramo</DRDBFOREIGNKEY>
		</DOMAINREADER>
      </FIELD>
      <FIELD>
      	<FIELDNAME>seccion</FIELDNAME>
      	<DOMAINREADER>
			<DRTYPE>db</DRTYPE>
			<DRDBTABLE>exp_finca</DRDBTABLE>
			<DRDBCOLUMNVALUE>seccion</DRDBCOLUMNVALUE>
			<DRDBCOLUMNALIAS>seccion</DRDBCOLUMNALIAS>
			<DRDBFOREIGNKEY>tramo</DRDBFOREIGNKEY>
			<DRDBFOREIGNKEY>unidad_constructiva</DRDBFOREIGNKEY>
			<DRDBFOREIGNKEY>ayuntamiento</DRDBFOREIGNKEY>
			<DRDBFOREIGNKEY>parroquia_subtramo</DRDBFOREIGNKEY>
			<DRDBFOREIGNKEY>numero_finca</DRDBFOREIGNKEY>
		</DOMAINREADER>
	  </FIELD>
      <FIELD>
        <FIELDNAME>superficie_finca_total</FIELDNAME>
        <VALIDATIONRULE>DOUBLE_POSITIVE</VALIDATIONRULE>
      </FIELD>
      <FIELD>
        <FIELDNAME>superficie_complementaria</FIELDNAME>
        <VALIDATIONRULE>DOUBLE_POSITIVE</VALIDATIONRULE>
      </FIELD>
      <FIELD>
        <FIELDNAME>deposito_previo_consignado_importe</FIELDNAME>
        <VALIDATIONRULE>DOUBLE_POSITIVE</VALIDATIONRULE>
      </FIELD>
      <FIELD>
        <FIELDNAME>anticipo_importe</FIELDNAME>
        <VALIDATIONRULE>DOUBLE_POSITIVE</VALIDATIONRULE>
      </FIELD>
      <FIELD>
        <FIELDNAME>mutuo_acuerdo_parcial_importe</FIELDNAME>
        <VALIDATIONRULE>DOUBLE_POSITIVE</VALIDATIONRULE>
      </FIELD>
      <FIELD>
        <FIELDNAME>limite_acuerdo_importe</FIELDNAME>
        <VALIDATIONRULE>DOUBLE_POSITIVE</VALIDATIONRULE>
      </FIELD>
      <FIELD>
        <FIELDNAME>mutuo_acuerdo_importe</FIELDNAME>
        <VALIDATIONRULE>DOUBLE_POSITIVE</VALIDATIONRULE>
      </FIELD>
      <FIELD>
        <FIELDNAME>pagos_varios_importe</FIELDNAME>
        <VALIDATIONRULE>DOUBLE_POSITIVE</VALIDATIONRULE>
      </FIELD>
      <FIELD>
        <FIELDNAME>deposito_previo_levantado_importe</FIELDNAME>
        <VALIDATIONRULE>DOUBLE_POSITIVE</VALIDATIONRULE>
      </FIELD>
      <FIELD>
        <FIELDNAME>importe_mejoras_complementarias</FIELDNAME>
        <VALIDATIONRULE>DOUBLE_POSITIVE</VALIDATIONRULE>
      </FIELD>
      <FIELD>
        <FIELDNAME>importe_pendiente_terrenos</FIELDNAME>
        <VALIDATIONRULE>DOUBLE_POSITIVE</VALIDATIONRULE>
      </FIELD>
      <FIELD>
        <FIELDNAME>importe_pendiente_mejoras</FIELDNAME>
        <VALIDATIONRULE>DOUBLE_POSITIVE</VALIDATIONRULE>
      </FIELD>
      <FIELD>
        <FIELDNAME>importe_pendiente_total</FIELDNAME>
        <VALIDATIONRULE>DOUBLE_POSITIVE</VALIDATIONRULE>
      </FIELD>
      <FIELD>
        <FIELDNAME>importe_pagado_total</FIELDNAME>
        <VALIDATIONRULE>DOUBLE_POSITIVE</VALIDATIONRULE>
      </FIELD>
    </RECORDSET>
  </LAYER>
</METADATA>
